argus_cli/README.md
argus_cli/__init__.py
argus_cli/arguments.py
argus_cli/helpers/__init__.py
argus_cli/helpers/collections.py
argus_cli/helpers/formatting.py
argus_cli/helpers/log.py
argus_cli/helpers/pagination.py
argus_cli/helpers/retry.py
argus_cli/parser.py
argus_cli/plugin.py
argus_cli/resources/config.yaml
argus_cli/settings.py
argus_cli/utils/__init__.py
argus_cli/utils/arguments.py
argus_cli/utils/formatting/__init__.py
argus_cli/utils/formatting/data_formats.py
argus_cli/utils/time.py
argus_plugins/README.md
argus_plugins/__init__.py
argus_plugins/__main__.py
argus_plugins/api_provider.py
argus_plugins/assets/__init__.py
argus_plugins/assets/imports.py
argus_plugins/cases/README.md
argus_plugins/cases/__init__.py
argus_plugins/cases/autocreate_case.py
argus_plugins/cases/autocreate_case_output_template.py
argus_plugins/cases/autocreate_yaml.py
argus_plugins/cases/basic.py
argus_plugins/cases/notification_check.py
argus_plugins/cases/remind.py
argus_plugins/cases/statistics.py
argus_plugins/cases/utils.py
argus_plugins/customer_networks/__init__.py
argus_plugins/customer_networks/customer_network.py
argus_plugins/customer_networks/helpers/__init__.py
argus_plugins/customer_networks/helpers/batch/__init__.py
argus_plugins/customer_networks/helpers/batch/create.py
argus_plugins/customer_networks/helpers/batch/destroy.py
argus_plugins/customer_networks/helpers/batch/update.py
argus_plugins/customer_networks/helpers/diff.py
argus_plugins/customer_networks/helpers/interactive/__init__.py
argus_plugins/customer_networks/helpers/interactive/create.py
argus_plugins/customer_networks/helpers/interactive/destroy.py
argus_plugins/customer_networks/helpers/interactive/update.py
argus_plugins/customer_networks/show.py
argus_plugins/customer_networks/update.py
argus_plugins/datastore/__init__.py
argus_plugins/datastore/synchronize.py
argus_plugins/enrichments.py
argus_plugins/events/__init__.py
argus_plugins/events/filter.py
argus_plugins/events/search.py
argus_toolbelt-6.30.1.dist-info/LICENSE
argus_toolbelt-6.30.1.dist-info/METADATA
argus_toolbelt-6.30.1.dist-info/WHEEL
argus_toolbelt-6.30.1.dist-info/entry_points.txt
argus_toolbelt-6.30.1.dist-info/RECORD
