Metadata-Version: 2.1
Name: argus-toolbelt
Version: 6.30.1
Summary: A framework for creating interactive commands with Argus' APIs
Home-page: https://mnemonic.io
License: ISC
Author: mnemonic
Author-email: opensource@mnemonic.no
Requires-Python: >=3.6.2,<4.0.0
Classifier: License :: OSI Approved
Classifier: Programming Language :: Python :: 3
Classifier: Programming Language :: Python :: 3.7
Classifier: Programming Language :: Python :: 3.8
Classifier: Programming Language :: Python :: 3.9
Classifier: Programming Language :: Python :: 3.10
Classifier: Programming Language :: Python :: 3.11
Classifier: Programming Language :: Python :: 3.12
Classifier: Programming Language :: Python :: 3.13
Provides-Extra: includes
Requires-Dist: argus-api (>=2.7.3,<4.0.0)
Requires-Dist: colorama (>=0.4.3,<0.5.0)
Requires-Dist: colorlog (>=4.7,<5.0)
Requires-Dist: dateparser
Requires-Dist: importlib_metadata (>3.5) ; python_version < "3.10"
Requires-Dist: jinja2 (>=2.11.3,<4.0.0)
Requires-Dist: pydantic (>=1.9.2,<2.0.0)
Requires-Dist: pyyaml (>=5.4.1,<7.0.0)
Requires-Dist: pyyaml-include (>=1.2,<2.0) ; extra == "includes"
Requires-Dist: requests (>=2.25,<3.0)
Requires-Dist: terminaltables (>=3.1,<4.0)
Requires-Dist: tqdm (>=4.56.0,<5.0.0)
Project-URL: Documentation, https://argus-toolbelt.docs.mnemonic.no
